view_export/__init__.py
view_export/models.py
view_export/urls.py
view_export/views.py
view_export/management/__init__.py
view_export/management/commands/__init__.py
view_export/management/commands/export_off_peak_views.py
django_view_export-1.0.0.dist-info/COPYING
django_view_export-1.0.0.dist-info/LICENSE
django_view_export-1.0.0.dist-info/METADATA
django_view_export-1.0.0.dist-info/WHEEL
django_view_export-1.0.0.dist-info/top_level.txt
django_view_export-1.0.0.dist-info/RECORD
