Metadata-Version: 2.1
Name: django-view-export
Version: 1.0.0
Summary: Export CSV reports of database views.
Home-page: https://gitlab.com/Sturm/django-view-export
Author: Ben Sturmfels
Author-email: ben@sturm.com.au
License: Apache License, Version 2.0
Project-URL: Source, https://gitlab.com/Sturm/django-view-export
Project-URL: Bug Reports, https://gitlab.com/Sturm/django-view-export/-/issues
Platform: UNKNOWN
Classifier: Development Status :: 5 - Production/Stable
Classifier: Environment :: Web Environment
Classifier: Framework :: Django
Classifier: Intended Audience :: Developers
Classifier: License :: OSI Approved :: Apache Software License
Classifier: Operating System :: OS Independent
Classifier: Programming Language :: Python
Classifier: Programming Language :: Python :: 3
Requires-Python: >=3.6
Requires-Dist: Django (>=3.2)
